Metadata-Version: 2.1
Name: PreproTools
Version: 1.1
Summary: A bunch of tool for NLP
Author: Ruben Hinojar
License: MIT
License-File: LICENSE.txt
